[{"QuestionID":1,"Text":"What was Tandem previous name?","CreatedBy":"DataTransform","CreatedDateTime":"2020-10-28T23:19:49.3915835Z","LastModifiedBy":"DataTransform","LastModifiedDateTime":"2020-10-28T23:19:49.3915835Z"},{"QuestionID":2,"Text":"In Shakespeare\u0027s play Julius Caesar, Caesar\u0027s last words were...","CreatedBy":"DataTransform","CreatedDateTime":"2020-10-28T23:19:49.3923328Z","LastModifiedBy":"DataTransform","LastModifiedDateTime":"2020-10-28T23:19:49.3923328Z"},{"QuestionID":3,"Text":"A group of tigers are referred to as:","CreatedBy":"DataTransform","CreatedDateTime":"2020-10-28T23:19:49.3923346Z","LastModifiedBy":"DataTransform","LastModifiedDateTime":"2020-10-28T23:19:49.3923346Z"},{"QuestionID":4,"Text":"What is the top speed an average cat can travel?","CreatedBy":"DataTransform","CreatedDateTime":"2020-10-28T23:19:49.3923358Z","LastModifiedBy":"DataTransform","LastModifiedDateTime":"2020-10-28T23:19:49.3923358Z"},{"QuestionID":5,"Text":"A cat can jump to _____ times its own height:","CreatedBy":"DataTransform","CreatedDateTime":"2020-10-28T23:19:49.3923369Z","LastModifiedBy":"DataTransform","LastModifiedDateTime":"2020-10-28T23:19:49.3923369Z"},{"QuestionID":6,"Text":"What is the only letter that doesn\u0027t appear in a US state name?","CreatedBy":"DataTransform","CreatedDateTime":"2020-10-28T23:19:49.3923383Z","LastModifiedBy":"DataTransform","LastModifiedDateTime":"2020-10-28T23:19:49.3923383Z"},{"QuestionID":7,"Text":"What is the name for a cow-bison hybrid?","CreatedBy":"DataTransform","CreatedDateTime":"2020-10-28T23:19:49.3923394Z","LastModifiedBy":"DataTransform","LastModifiedDateTime":"2020-10-28T23:19:49.3923394Z"},{"QuestionID":8,"Text":"What is the largest freshwater lake in the world?","CreatedBy":"DataTransform","CreatedDateTime":"2020-10-28T23:19:49.3923405Z","LastModifiedBy":"DataTransform","LastModifiedDateTime":"2020-10-28T23:19:49.3923405Z"},{"QuestionID":9,"Text":"In a website address bar, what does WWW stand for?","CreatedBy":"DataTransform","CreatedDateTime":"2020-10-28T23:19:49.3923415Z","LastModifiedBy":"DataTransform","LastModifiedDateTime":"2020-10-28T23:19:49.3923415Z"},{"QuestionID":10,"Text":"In a game of bingo, what number is represented by the name two little ducks?","CreatedBy":"DataTransform","CreatedDateTime":"2020-10-28T23:19:49.3923426Z","LastModifiedBy":"DataTransform","LastModifiedDateTime":"2020-10-28T23:19:49.3923426Z"},{"QuestionID":11,"Text":"According to Greek mythology, who was the first woman on Earth?","CreatedBy":"DataTransform","CreatedDateTime":"2020-10-28T23:19:49.3923437Z","LastModifiedBy":"DataTransform","LastModifiedDateTime":"2020-10-28T23:19:49.3923437Z"},{"QuestionID":12,"Text":"In which European city would you find Orly airport?","CreatedBy":"DataTransform","CreatedDateTime":"2020-10-28T23:19:49.3923448Z","LastModifiedBy":"DataTransform","LastModifiedDateTime":"2020-10-28T23:19:49.3923448Z"},{"QuestionID":13,"Text":"Where would you find the Sea of Tranquility?","CreatedBy":"DataTransform","CreatedDateTime":"2020-10-28T23:19:49.3923458Z","LastModifiedBy":"DataTransform","LastModifiedDateTime":"2020-10-28T23:19:49.3923458Z"},{"QuestionID":14,"Text":"Which artist painted \u0027Girl with a Pearl Earrin\u0027?","CreatedBy":"DataTransform","CreatedDateTime":"2020-10-28T23:19:49.3923469Z","LastModifiedBy":"DataTransform","LastModifiedDateTime":"2020-10-28T23:19:49.3923469Z"},{"QuestionID":15,"Text":"What is the official name for the \u0027hashtag\u0027 symbol?","CreatedBy":"DataTransform","CreatedDateTime":"2020-10-28T23:19:49.3923479Z","LastModifiedBy":"DataTransform","LastModifiedDateTime":"2020-10-28T23:19:49.3923479Z"},{"QuestionID":16,"Text":"Not American at all, where is apple pie from?","CreatedBy":"DataTransform","CreatedDateTime":"2020-10-28T23:19:49.392349Z","LastModifiedBy":"DataTransform","LastModifiedDateTime":"2020-10-28T23:19:49.392349Z"},{"QuestionID":17,"Text":"What is the national animal of Scotland?","CreatedBy":"DataTransform","CreatedDateTime":"2020-10-28T23:19:49.39235Z","LastModifiedBy":"DataTransform","LastModifiedDateTime":"2020-10-28T23:19:49.39235Z"},{"QuestionID":18,"Text":"Where in the world is the only place where Canada is *due south*","CreatedBy":"DataTransform","CreatedDateTime":"2020-10-28T23:19:49.392356Z","LastModifiedBy":"DataTransform","LastModifiedDateTime":"2020-10-28T23:19:49.392356Z"},{"QuestionID":19,"Text":"Approximately how many grapes go into a bottle of wine?","CreatedBy":"DataTransform","CreatedDateTime":"2020-10-28T23:19:49.3923571Z","LastModifiedBy":"DataTransform","LastModifiedDateTime":"2020-10-28T23:19:49.3923571Z"},{"QuestionID":20,"Text":"How much does a US One Dollar Bill cost to make?","CreatedBy":"DataTransform","CreatedDateTime":"2020-10-28T23:19:49.3923582Z","LastModifiedBy":"DataTransform","LastModifiedDateTime":"2020-10-28T23:19:49.3923582Z"},{"QuestionID":21,"Text":"The Vatican bank has the only ATM in the world that allows users to do what?","CreatedBy":"DataTransform","CreatedDateTime":"2020-10-28T23:19:49.3923592Z","LastModifiedBy":"DataTransform","LastModifiedDateTime":"2020-10-28T23:19:49.3923592Z"}]